cmrseq/__init__.py
cmrseq/_exceptions.py
cmrseq/plotting.py
cmrseq/contrib/_2D_flow.py
cmrseq/contrib/_4DFlow.py
cmrseq/contrib/_4DRadial.py
cmrseq/contrib/__init__.py
cmrseq/contrib/_cardiac_diffusion.py
cmrseq/core/__init__.py
cmrseq/core/_omatrix.py
cmrseq/core/_sequence.py
cmrseq/core/_system.py
cmrseq/core/bausteine/__init__.py
cmrseq/core/bausteine/_adc.py
cmrseq/core/bausteine/_base.py
cmrseq/core/bausteine/_delay.py
cmrseq/core/bausteine/_gradients.py
cmrseq/core/bausteine/_rf.py
cmrseq/io/__init__.py
cmrseq/io/_json.py
cmrseq/io/_pulseq.py
cmrseq/parametric_definitions/__init__.py
cmrseq/parametric_definitions/diffusion.py
cmrseq/parametric_definitions/excitation.py
cmrseq/parametric_definitions/velocity.py
cmrseq/parametric_definitions/preparation/__init__.py
cmrseq/parametric_definitions/preparation/_spinlock_prepulse.py
cmrseq/parametric_definitions/readout/__init__.py
cmrseq/parametric_definitions/readout/_cartesian_single_lines.py
cmrseq/parametric_definitions/readout/_epi.py
cmrseq/parametric_definitions/readout/_radial.py
cmrseq/parametric_definitions/readout/_spiral.py
cmrseq/parametric_definitions/sequences/__init__.py
cmrseq/parametric_definitions/sequences/_gradient_echo.py
cmrseq/parametric_definitions/sequences/_spin_echo.py
cmrseq/parametric_definitions/sequences/_ssfp.py
cmrseq/utils/__init__.py
cmrseq/utils/_diffusion.py
cmrseq/utils/_general.py
cmrseq/utils/_report.py
cmrseq/utils/_transformations.py
cmrseq-0.27.1.dist-info/LICENSE
cmrseq-0.27.1.dist-info/METADATA
cmrseq-0.27.1.dist-info/WHEEL
cmrseq-0.27.1.dist-info/top_level.txt
cmrseq-0.27.1.dist-info/RECORD
