Metadata-Version: 2.1
Name: cmrseq
Version: 0.27.1
Summary: Define your MRI sequences in pure python!
Author-email: Jonathan Weine <weine@biomed.ee.ethz.ch>, Charles McGrath <mcgrath@biomed.ee.ethz.ch>
License: GPL-3.0-or-later
Project-URL: Documentation, https://people.ee.ethz.ch/~mcgrathc/cmrseq/latest/index.html
Project-URL: Source, https://gitlab.ethz.ch/ibt-cmr/mri_simulation/cmrseq
Project-URL: Institute, https://cmr.ethz.ch/
Keywords: MRI,pulse sequence,cardiac,simulation,medical imaging
Classifier: Development Status :: 4 - Beta
Classifier: Intended Audience :: Science/Research
Classifier: License :: OSI Approved :: GNU General Public License v3 or later (GPLv3+)
Classifier: Programming Language :: Python :: 3
Classifier: Programming Language :: Python :: 3.10
Classifier: Programming Language :: Python :: 3.11
Classifier: Topic :: Scientific/Engineering :: Medical Science Apps.
Requires-Python: >=3.10
License-File: LICENSE
Requires-Dist: numpy
Requires-Dist: pint
Requires-Dist: matplotlib
Requires-Dist: tqdm
Requires-Dist: scipy>=1.12
Requires-Dist: sigpy
